m_singleton-0.3.dist-info/DESCRIPTION.rst
m_singleton-0.3.dist-info/METADATA
m_singleton-0.3.dist-info/RECORD
m_singleton-0.3.dist-info/WHEEL
m_singleton-0.3.dist-info/metadata.json
m_singleton-0.3.dist-info/top_level.txt
mobio/libs/Singleton/__init__.py
