Metadata-Version: 2.0
Name: m-singleton
Version: 0.3
Summary: Setup normal class to SingletonClass
Home-page: https://github.com/mobiovn
Author: MOBIO
Author-email: contact@mobio.vn
License: MIT
Platform: UNKNOWN
